consumptioncli/__init__.py
consumptioncli/__main__.py
consumptioncli/commands/ConsumableCommandHandler.py
consumptioncli/commands/PersonnelCommandHandler.py
consumptioncli/commands/SeriesCommandHandler.py
consumptioncli/commands/TagCommandHandler.py
consumptioncli/commands/__init__.py
consumptioncli/commands/input.py
consumptioncli/commands/messages.py
consumptioncli/config.py
consumptioncli/constants.py
consumptioncli/display/__init__.py
consumptioncli/display/formatting.py
consumptioncli/display/lists/ConsumableList.py
consumptioncli/display/lists/PersonnelList.py
consumptioncli/display/lists/SeriesList.py
consumptioncli/display/lists/TagList.py
consumptioncli/display/lists/__init__.py
consumptioncli/display/lists/list_handling.py
consumptioncli/display/stats.py
consumptioncli/display/types.py
consumptioncli/display/views/ConsumableView.py
consumptioncli/display/views/PersonnelView.py
consumptioncli/display/views/SeriesView.py
consumptioncli/display/views/__init__.py
consumptioncli/logging.py
consumptioncli/parsing/BetterNamespace.py
consumptioncli/parsing/MainParser.py
consumptioncli/parsing/__init__.py
consumptioncli/parsing/actions.py
consumptioncli/parsing/consumable_parsers.py
consumptioncli/parsing/operators.py
consumptioncli/parsing/parsing.py
consumptioncli/parsing/personnel_parsers.py
consumptioncli/parsing/series_parsers.py
consumptioncli/parsing/tag_parsers.py
consumptioncli/parsing/types.py
consumptioncli/utils.py
consumptioncli-3.1.0.dist-info/WHEEL
consumptioncli-3.1.0.dist-info/entry_points.txt
consumptioncli-3.1.0.dist-info/METADATA
consumptioncli-3.1.0.dist-info/RECORD
