Metadata-Version: 2.3
Name: consumptioncli
Version: 3.1.0
Summary: A CLI tool for tracking consumption of media including Novels, Movies, TV Series and more.
Author: track44
Author-email: track44 <trackfortyfour@proton.me>
License:                     GNU GENERAL PUBLIC LICENSE
Classifier: Development Status :: 4 - Beta
Classifier: Environment :: Console
Classifier: Programming Language :: Python :: 3
Classifier: License :: OSI Approved :: GNU General Public License v3 (GPLv3)
Classifier: Operating System :: OS Independent
Classifier: Natural Language :: English
Requires-Dist: tabulate>=0.9.0
Requires-Dist: consumptionbackend~=3.1.0
Requires-Dist: platformdirs~=4.5.1
Requires-Python: >=3.14
Project-URL: Homepage, https://github.com/track-44/consumptionCLI
Project-URL: Bug Tracker, https://github.com/track-44/consumptionCLI/issues
